MOBiceps/__init__.py
MOBiceps/clean_expression_table.py
MOBiceps/container2img.py
MOBiceps/container_extraction.py
MOBiceps/convertRawMP.py
MOBiceps/convert_mzXML2img.py
MOBiceps/create_expression_table.py
MOBiceps/dataClasses.py
MOBiceps/expression_table.py
MOBiceps/featureSelector.py
MOBiceps/foldsConstruction.py
MOBiceps/modifiedYellowbrick.py
MOBiceps/modifiedYellowbrick_ROCAUC.py
MOBiceps/mzXML2npyContainer.py
MOBiceps/npy2png.py
MOBiceps/rfePlusPlusWF.py
MOBiceps-0.1.4.dist-info/LICENSE
MOBiceps-0.1.4.dist-info/METADATA
MOBiceps-0.1.4.dist-info/WHEEL
MOBiceps-0.1.4.dist-info/top_level.txt
MOBiceps-0.1.4.dist-info/RECORD
